rechu/__init__.py
rechu/__main__.py
rechu/alembic.ini
rechu/database.py
rechu/py.typed
rechu/settings.py
rechu/settings.toml
rechu/alembic/env.py
rechu/alembic/versions/24c54f418b92_add_cascade_deletes_for_products_.py
rechu/alembic/versions/3b0cfa853967_increase_gtin_size.py
rechu/alembic/versions/5a5bf02e8988_add_product_metadata_range.py
rechu/alembic/versions/81b6d004d3c5_add_shop_metadata_and_foreign_key.py
rechu/alembic/versions/8ef12eb24650_add_receipt_item_extracted_quantity_.py
rechu/alembic/versions/9d5f6a8f4944_drop_foreign_key_for_receipt_shop.py
rechu/alembic/versions/aaff17ed83d8_add_product_matchers.py
rechu/alembic/versions/b1a7a91c8de8_add_receipt_item_position_fields.py
rechu/alembic/versions/d6854aeb9756_add_product_relation_and_shop.py
rechu/command/__init__.py
rechu/command/alembic.py
rechu/command/base.py
rechu/command/config.py
rechu/command/create.py
rechu/command/delete.py
rechu/command/dump.py
rechu/command/match.py
rechu/command/read.py
rechu/command/new/__init__.py
rechu/command/new/input.py
rechu/command/new/step/__init__.py
rechu/command/new/step/base.py
rechu/command/new/step/discounts.py
rechu/command/new/step/edit.py
rechu/command/new/step/help.py
rechu/command/new/step/meta.py
rechu/command/new/step/products.py
rechu/command/new/step/quit.py
rechu/command/new/step/read.py
rechu/command/new/step/view.py
rechu/command/new/step/write.py
rechu/inventory/__init__.py
rechu/inventory/base.py
rechu/inventory/products.py
rechu/inventory/shops.py
rechu/io/__init__.py
rechu/io/base.py
rechu/io/products.py
rechu/io/receipt.py
rechu/io/shops.py
rechu/matcher/__init__.py
rechu/matcher/base.py
rechu/matcher/product.py
rechu/models/__init__.py
rechu/models/base.py
rechu/models/product.py
rechu/models/receipt.py
rechu/models/shop.py
rechu/types/__init__.py
rechu/types/decorator.py
rechu/types/quantized.py
rechu/types/measurable/__init__.py
rechu/types/measurable/base.py
rechu/types/measurable/decorator.py
rechu/types/measurable/quantity.py
rechu-0.0.2.dist-info/licenses/LICENSE
rechu-0.0.2.dist-info/METADATA
rechu-0.0.2.dist-info/WHEEL
rechu-0.0.2.dist-info/entry_points.txt
rechu-0.0.2.dist-info/top_level.txt
rechu-0.0.2.dist-info/RECORD
