Metadata-Version: 2.4
Name: rechu
Version: 0.0.2
Summary: Receipt cataloging hub for detailed personal finance tracking
Author-email: Leon Helwerda <leon.helwerda@gmail.com>
License-Expression: MIT
Project-URL: Documentation, https://lhelwerd.github.io/rechu/
Project-URL: Source Code, https://github.com/lhelwerd/rechu
Project-URL: Changelog, https://github.com/lhelwerd/rechu/blob/main/CHANGELOG.md
Project-URL: Download, https://github.com/lhelwerd/rechu/releases/latest
Project-URL: PyPI, https://pypi.org/project/rechu
Project-URL: Issues, https://github.com/lhelwerd/rechu/issues
Project-URL: Pull Requests, https://github.com/lhelwerd/rechu/pulls
Project-URL: CI: GitHub Actions, https://github.com/lhelwerd/rechu/actions
Project-URL: CI: Coveralls, https://coveralls.io/github/lhelwerd/rechu?branch=main
Project-URL: CI: SonarCloud, https://sonarcloud.io/summary/new_code?id=lhelwerd_rechu
Keywords: personal finance,receipts,cataloging
Classifier: Development Status :: 3 - Alpha
Classifier: Programming Language :: Python
Classifier: Programming Language :: Python :: 3.10
Classifier: Programming Language :: Python :: 3.11
Classifier: Programming Language :: Python :: 3.12
Classifier: Programming Language :: Python :: 3.13
Classifier: Programming Language :: Python :: 3.14
Classifier: Topic :: Office/Business :: Financial
Requires-Python: <3.15,>=3.10
License-File: LICENSE
Requires-Dist: alembic==1.16.4
Requires-Dist: Pint==0.24.4
Requires-Dist: python-dateutil==2.9.0.post0
Requires-Dist: PyYAML==6.0.2
Requires-Dist: SQLAlchemy==2.0.42
Requires-Dist: tomlkit==0.13.3
Requires-Dist: typing_extensions==4.14.1
Provides-Extra: postgres
Requires-Dist: psycopg2-binary==2.9.10; extra == "postgres"
Dynamic: license-file
